ShiyanlouWangluojiaochengHeji20160904/README.md
ShiyanlouWangluojiaochengHeji20160904/__init__.py
ShiyanlouWangluojiaochengHeji20160904/__main__.py
ShiyanlouWangluojiaochengHeji20160904/file.epub
ShiyanlouWangluojiaochengHeji20160904/index.html
ShiyanlouWangluojiaochengHeji20160904/css/__init__.py
ShiyanlouWangluojiaochengHeji20160904/css/annotations.css
ShiyanlouWangluojiaochengHeji20160904/css/main.css
ShiyanlouWangluojiaochengHeji20160904/css/normalize.css
ShiyanlouWangluojiaochengHeji20160904/css/popup.css
ShiyanlouWangluojiaochengHeji20160904/font/__init__.py
ShiyanlouWangluojiaochengHeji20160904/font/fontello.eot
ShiyanlouWangluojiaochengHeji20160904/font/fontello.svg
ShiyanlouWangluojiaochengHeji20160904/font/fontello.ttf
ShiyanlouWangluojiaochengHeji20160904/font/fontello.woff
ShiyanlouWangluojiaochengHeji20160904/img/__init__.py
ShiyanlouWangluojiaochengHeji20160904/img/annotator-glyph-sprite.png
ShiyanlouWangluojiaochengHeji20160904/img/annotator-icon-sprite.png
ShiyanlouWangluojiaochengHeji20160904/img/apple-touch-icon.png
ShiyanlouWangluojiaochengHeji20160904/img/cancelfullscreen.png
ShiyanlouWangluojiaochengHeji20160904/img/close.png
ShiyanlouWangluojiaochengHeji20160904/img/fullscreen.png
ShiyanlouWangluojiaochengHeji20160904/img/loader.gif
ShiyanlouWangluojiaochengHeji20160904/img/menu-icon.png
ShiyanlouWangluojiaochengHeji20160904/img/save.png
ShiyanlouWangluojiaochengHeji20160904/img/saved.png
ShiyanlouWangluojiaochengHeji20160904/img/settings-s.png
ShiyanlouWangluojiaochengHeji20160904/img/settings.png
ShiyanlouWangluojiaochengHeji20160904/img/star.png
ShiyanlouWangluojiaochengHeji20160904/js/__init__.py
ShiyanlouWangluojiaochengHeji20160904/js/epub.js
ShiyanlouWangluojiaochengHeji20160904/js/epub.min.js
ShiyanlouWangluojiaochengHeji20160904/js/epub.min.map
ShiyanlouWangluojiaochengHeji20160904/js/hooks.min.js
ShiyanlouWangluojiaochengHeji20160904/js/hooks.min.map
ShiyanlouWangluojiaochengHeji20160904/js/reader.js
shiyanlou_wangluojiaocheng_heji_20160904-2024.3.2.0.dist-info/METADATA
shiyanlou_wangluojiaocheng_heji_20160904-2024.3.2.0.dist-info/WHEEL
shiyanlou_wangluojiaocheng_heji_20160904-2024.3.2.0.dist-info/entry_points.txt
shiyanlou_wangluojiaocheng_heji_20160904-2024.3.2.0.dist-info/top_level.txt
shiyanlou_wangluojiaocheng_heji_20160904-2024.3.2.0.dist-info/RECORD
